{
  "character_id": "ed013856",
  "name": "Kaysha",
  "visual_description": "A smiling young adult woman with an oval face and fair skin. She has short, wavy blonde hair with a side part and bangs, and blue eyes. She has a slender build and appears to be of average height. She has no distinctive features.",
  "personality": "Alternative, cheerful, perky",
  "physical_description": "A young adult woman with fair skin and an oval face. She has blue eyes and European features, accentuated by high cheekbones and a warm smile. Her short, wavy blonde hair is styled in a bob with side-swept bangs. She has an average height and slender build.",
  "reference_image_path": "/app/data/characters/ed013856_ref.png",
  "tags": [],
  "created_at": "2025-10-16T20:19:21.417331",
  "updated_at": "2025-10-17T01:01:46.342123",
  "metadata": {},
  "age": "young adult",
  "skin_tone": "fair",
  "face_description": "Oval face with feminine features, blue eyes, and European features. High cheekbones, and a bright smile.",
  "hair_description": "Short, wavy blonde hair, styled in a bob with side-swept bangs.",
  "body_description": "Average height with a slender build."
}